[
  {
    "image": "https://image.pollinations.ai/prompt/Futuristic%20city%20skyline%20with%20interconnected%205G%20network%20nodes%20glowing%20brightly%2C%20Featured%2C%20high%20detail%2C%20vibrant%2C%20professional%20photo?width=600&height=400&seed=729730944&nologo=true",
    "dataAiHint": "Futuristic city",
    "category": "Featured",
    "title": "Revolutionizing Connectivity: 5G's Profound Impact on Modern Society",
    "articleContent": "5G technology, the fifth generation of cellular network technology, is rapidly transforming the way we live, work, and interact with the world.  Its impact extends far beyond faster download speeds, representing a fundamental shift in how we connect and engage with digital experiences. This article delves into the multifaceted impact of 5G on society, exploring its benefits, challenges, and potential future implications.\n\nOne of the most immediate and noticeable effects of 5G is the significant improvement in network speed and capacity.  Compared to its predecessors, 5G offers drastically faster download and upload speeds, lower latency (the delay in data transmission), and a far greater capacity to handle multiple devices simultaneously. This translates to smoother streaming, quicker downloads, and more reliable connectivity, even in crowded areas.  This enhanced connectivity is paving the way for a variety of new applications and services, impacting various sectors of society.\n\nThe impact on the healthcare industry is particularly profound. 5G's low latency and high bandwidth enable remote surgery, enabling surgeons to operate on patients remotely with minimal delay.  This is a game-changer for healthcare access, particularly in rural or underserved areas.  Furthermore, 5G facilitates the use of wearable sensors and remote patient monitoring devices, allowing for real-time health data collection and analysis, leading to earlier disease detection and more effective treatment plans.  This improved connectivity enhances the quality of care and improves patient outcomes.\n\nIn the manufacturing sector, 5G is revolutionizing industrial processes through the implementation of smart factories and automation.  High-speed, reliable data transfer allows for seamless communication between machines and sensors, enabling real-time monitoring, control, and optimization of production lines. This improves efficiency, reduces downtime, and enhances overall productivity.  The integration of robotics and artificial intelligence is further enhanced by 5G's capabilities, creating a more sophisticated and automated manufacturing environment.\n\nTransportation is also undergoing a dramatic transformation with the advent of 5G.  Self-driving cars and autonomous vehicles rely heavily on the ability to communicate and exchange data rapidly and reliably.  5G’s low latency makes it possible for these vehicles to navigate safely and efficiently, avoiding collisions and optimizing traffic flow.  The development of smart traffic management systems is also accelerated by 5G, leading to reduced congestion and improved transportation efficiency.\n\nThe entertainment industry is benefiting significantly from 5G’s capabilities.  The high-speed connectivity enables the delivery of high-quality streaming video and virtual reality (VR) and augmented reality (AR) experiences.  This is opening up new possibilities for immersive gaming, interactive entertainment, and virtual events.  The quality and responsiveness of these experiences are greatly enhanced, leading to a more immersive and engaging entertainment experience.\n\nHowever, the widespread adoption of 5G also presents several challenges.  The rollout of 5G infrastructure requires significant investment in new infrastructure, including the deployment of new cell towers and antennas.  This can be costly and time-consuming, particularly in remote or underserved areas.  Furthermore, concerns regarding the potential health effects of 5G radiation remain, requiring further research and public education to address these concerns and build trust.\n\nAnother significant concern is cybersecurity.  With the increased connectivity enabled by 5G, the potential for cyberattacks and data breaches also increases.  Robust cybersecurity measures and strong data protection protocols are essential to mitigate these risks and ensure the safe and secure use of 5G technology.  The development and implementation of advanced security technologies are critical to safeguarding sensitive data and ensuring the integrity of 5G networks.\n\nThe potential future implications of 5G are vast and far-reaching.  As 5G technology matures and becomes more widely adopted, we can expect to see even more transformative applications and services.  The Internet of Things (IoT), with its interconnected network of devices, will be significantly enhanced by 5G, leading to smart homes, smart cities, and other innovative solutions.  The advancements in artificial intelligence and machine learning will also be propelled by 5G, leading to smarter and more efficient systems across various sectors.\n\nIn conclusion, 5G technology is a powerful force of innovation, impacting nearly every aspect of modern society.  While challenges exist, the potential benefits of this transformative technology are immense.  As 5G continues to evolve and become more integrated into our daily lives, we can expect to see even more significant changes and advancements across various industries and facets of human experience, shaping a future characterized by enhanced connectivity, efficiency, and innovation.",
    "keyTakeaways": [
      "5G offers significantly faster speeds, lower latency, and higher capacity than previous generations.",
      "5G is revolutionizing healthcare with remote surgery and remote patient monitoring.",
      "5G is transforming manufacturing with smart factories and automation.",
      "5G is enabling self-driving cars and autonomous vehicles.",
      "5G is enhancing the entertainment industry with high-quality streaming and VR/AR experiences.",
      "5G presents challenges in infrastructure costs, potential health concerns, and cybersecurity risks."
    ],
    "conclusion": "5G technology is reshaping the landscape of modern society, offering unprecedented opportunities for innovation and progress across diverse sectors. While challenges related to infrastructure, health concerns, and cybersecurity need to be addressed, the potential benefits of this revolutionary technology are undeniable.  As 5G continues its global rollout and integration, it promises to further transform how we live, work, and interact with the world, shaping a future of enhanced connectivity, efficiency, and innovation."
  },
  {
    "image": "https://image.pollinations.ai/prompt/A%20diverse%20group%20of%20people%20looking%20at%20laptop%20screens%20displaying%20stock%20market%20graphs%2C%20Featured%2C%20high%20detail%2C%20vibrant%2C%20professional%20photo?width=600&height=400&seed=652536000&nologo=true",
    "dataAiHint": "A diverse",
    "category": "Featured",
    "title": "Beginner's Guide to Investing in the Stock Market for Success",
    "articleContent": "Investing in the stock market can seem daunting, especially for beginners.  The sheer volume of information, jargon, and potential risks can be overwhelming. However, with a structured approach and a willingness to learn, anyone can navigate the world of stock market investing. This beginner's guide will provide you with the foundational knowledge you need to start your investing journey confidently.\n\n**Understanding the Basics: Stocks and the Stock Market**\n\nBefore diving into the specifics, it's crucial to grasp the fundamental concepts.  The stock market is essentially a marketplace where shares of publicly traded companies are bought and sold.  These shares, or stocks, represent ownership in a company. When you buy stock, you become a shareholder, owning a small piece of that company.  The price of a stock fluctuates based on supply and demand, influenced by various factors including company performance, economic conditions, and investor sentiment.\n\n**Types of Stock Market Investments**\n\nThere are several ways to invest in the stock market.  Individual stocks represent direct ownership in a specific company.  They offer the potential for high returns but also carry higher risk.  Mutual funds pool money from multiple investors to invest in a diversified portfolio of stocks, bonds, or other assets.  They offer diversification and professional management, reducing risk but potentially limiting returns compared to individual stocks. Exchange-Traded Funds (ETFs) are similar to mutual funds but trade like individual stocks on exchanges, offering greater flexibility.\n\n**Setting Your Investment Goals and Risk Tolerance**\n\nBefore investing a single dollar, it's essential to define your financial goals and assess your risk tolerance.  What are you hoping to achieve with your investments?  Are you saving for retirement, a down payment on a house, or something else?  Understanding your goals will help you determine your investment timeframe and the level of risk you're comfortable taking.  Risk tolerance refers to your ability to withstand potential losses.  Conservative investors prefer lower-risk investments, while aggressive investors are willing to accept higher risk for potentially greater returns.  Your age, financial situation, and investment horizon should all factor into determining your risk tolerance.\n\n**Research and Due Diligence: Choosing the Right Investments**\n\nOnce you've defined your goals and risk tolerance, you can start researching potential investments.  This involves analyzing a company's financial statements, understanding its business model, and assessing its competitive landscape.  While this may seem complex, many resources are available to help.  Websites like Yahoo Finance and Google Finance offer company profiles and financial data.  News articles and industry reports can provide insights into a company's performance and future prospects.  However, remember to always be critical of the information you find and consider consulting with a financial advisor for personalized guidance.\n\n**Diversification: Spreading Your Risk**\n\nDiversification is a crucial investment strategy that involves spreading your investments across different asset classes, industries, and geographic regions.  By diversifying your portfolio, you reduce your risk of significant losses if one particular investment underperforms.  For example, you might invest in a mix of stocks, bonds, and real estate.  Within stocks, you might diversify across different sectors, such as technology, healthcare, and energy.\n\n**Dollar-Cost Averaging: A Strategic Approach**\n\nDollar-cost averaging (DCA) is an investment strategy that involves investing a fixed amount of money at regular intervals, regardless of the market's price fluctuations.  This strategy helps to reduce the impact of market volatility, as you buy more shares when prices are low and fewer shares when prices are high.  DCA is a particularly effective strategy for long-term investors who are less concerned about short-term market fluctuations.\n\n**The Importance of Long-Term Investing**\n\nThe stock market can be volatile in the short term, with prices fluctuating up and down.  However, over the long term, the market has historically shown a tendency to rise.  Long-term investing allows you to ride out short-term market downturns and benefit from the market's long-term growth potential.  This is why it is crucial to have a well-defined investment plan and stick to it, especially during periods of market uncertainty.\n\n**Managing Your Portfolio: Regular Monitoring and Adjustments**\n\nOnce you've built your portfolio, it's important to monitor it regularly and make adjustments as needed.  This might involve rebalancing your portfolio to maintain your desired asset allocation or selling investments that are no longer performing well.  Regular monitoring also helps you stay informed about market trends and any potential risks affecting your investments.\n\n**Seeking Professional Advice: Financial Advisors**\n\nWhile this guide provides a foundational understanding of stock market investing, seeking professional advice from a financial advisor can be invaluable, especially for beginners.  A financial advisor can help you develop a personalized investment plan, manage your portfolio, and navigate the complexities of the stock market.  They can provide guidance based on your individual financial goals, risk tolerance, and time horizon.\n\n**Conclusion:**\n\nInvesting in the stock market can be a rewarding way to build wealth over time.  However, it's essential to approach it with a well-defined plan, a thorough understanding of the risks involved, and a commitment to ongoing learning.  By following the principles outlined in this guide and seeking professional advice when needed, beginners can increase their chances of achieving their investment goals.",
    "keyTakeaways": [
      "Define your financial goals and risk tolerance before investing.",
      "Understand different investment options: individual stocks, mutual funds, and ETFs.",
      "Research and perform due diligence on potential investments.",
      "Diversify your portfolio to reduce risk.",
      "Consider dollar-cost averaging for a strategic approach.",
      "Long-term investing is key for maximizing returns."
    ],
    "conclusion": "Investing in the stock market offers the potential for significant financial growth, but it's crucial to approach it strategically.  By understanding the basics, conducting thorough research, diversifying your portfolio, and employing sound investment strategies, beginners can confidently embark on their investing journey. Remember, consistent learning and seeking professional advice when needed are essential for long-term success."
  },
  {
    "image": "https://image.pollinations.ai/prompt/A%20vibrant%20digital%20painting%20showcasing%20a%20diverse%20range%20of%20digital%20art%20styles%20and%20tools%2C%20Featured%2C%20high%20detail%2C%20vibrant%2C%20professional%20photo?width=600&height=400&seed=549868293&nologo=true",
    "dataAiHint": "A vibrant",
    "category": "Featured",
    "title": "Unlock Your Inner Artist: A Guide to Digital Art Creation",
    "articleContent": "The digital art world is a vibrant tapestry woven from pixels, imagination, and technological prowess.  Unlike traditional art forms, digital art offers unparalleled flexibility and accessibility, empowering artists of all skill levels to explore their creativity. But the creative process, while exciting, can often feel daunting. This comprehensive guide delves into the multifaceted journey of creating digital art, from initial inspiration to the final polished piece.\n\n**Phase 1: The Spark of Inspiration – Finding Your Muse**\n\nThe creative process begins long before the first brushstroke (or pixel placement).  Inspiration can strike anywhere, anytime. It could be a breathtaking sunset, a captivating photograph, a captivating piece of music, or even a fleeting thought.  Keeping a sketchbook, digital or physical, is invaluable for jotting down ideas, sketching rough concepts, and collecting visual references.  Actively seeking inspiration – exploring museums, art galleries, nature, or online art communities – fuels the creative fire. Experiment with different prompts or themes to break creative blocks. Consider mood boards, collecting images and textures to inspire your artwork and solidify your vision.\n\n**Phase 2: Concept Development – Shaping Your Vision**\n\nOnce inspiration strikes, it's time to shape your vision into a tangible concept. This involves refining your initial idea, developing the narrative or message you want to convey, and making crucial decisions about composition, color palettes, and style.  Consider the overall mood you want to evoke – is it serene, chaotic, mysterious, or joyful?  Sketching and planning are crucial; even digital artists benefit from traditional methods of outlining and sketching. These preliminary steps help solidify your understanding of the piece and prevent unexpected challenges during the execution phase.\n\n**Phase 3: Software Selection and Tool Familiarity**\n\nThe digital art world boasts a vast array of software options, each with its unique strengths and weaknesses. Popular choices include Adobe Photoshop, Procreate, Clip Studio Paint, and Krita.  The best software choice depends on your artistic style, budget, and technical preferences.  Once you've chosen your software, invest time in learning its features. Familiarizing yourself with the tools – brushes, layers, selection tools, filters – is essential for efficient and creative workflow. Online tutorials, workshops, and practice exercises are invaluable resources for mastering your chosen software.\n\n**Phase 4: The Creation Process – Bringing Your Vision to Life**\n\nThis is where the magic happens.  Using your chosen software, you translate your sketches and concept into a digital masterpiece.  Begin with a solid foundation, often involving creating a new canvas and establishing your base colors or layers.  Layer management is crucial in digital art, allowing for easy adjustments and experimentation.  Don't be afraid to experiment with different techniques and brushes.  Consider adding textures, using gradients, and adjusting lighting to enhance your artwork's depth and realism.\n\n**Phase 5: Refinement and Detailing – Polishing Your Gem**\n\nOnce your artwork nears completion, the refinement stage ensures a professional-looking final piece. This often involves subtle adjustments to color, contrast, and sharpness. Zoom in to identify areas that need extra attention.  Consider adding subtle details to enhance the overall impact.   This is the stage to correct any imperfections, enhance details, and ensure visual harmony in your artwork. Digital art often demands meticulous detail work, making this a critical phase.\n\n**Phase 6: Feedback and Iteration – Learning and Growing**\n\nSeeking feedback from fellow artists, peers, or online communities can provide valuable insights and perspectives.  Constructive criticism can help you identify weaknesses in your artwork and improve your technique.  Don't be afraid to make changes based on feedback.  Iteration is an integral part of the creative process.  Embrace feedback as an opportunity to learn and grow as an artist.\n\n**Phase 7: Sharing and Presentation – Showcasing Your Work**\n\nOnce you're satisfied with your artwork, it's time to share your creation with the world. Consider creating a professional online portfolio showcasing your digital art. Platforms like ArtStation, Behance, and DeviantArt are excellent options.  When presenting your work, ensure high-quality images. Also, include information about the artwork's concept, creative process, and software used.  Online platforms offer a chance to receive valuable feedback and connect with other artists.\n\n**Phase 8: Copyright and Protection – Safeguarding Your Art**\n\nProtecting your intellectual property is crucial. Copyright your digital art to safeguard your creative work and prevent unauthorized use or reproduction. Understanding copyright laws and digital rights management is vital for protecting your creative investment.  This step secures your ownership and prevents your art from being exploited without your consent.\n\nThe digital art process isn't linear; it's iterative and often involves revisiting earlier stages. Embrace the journey, experiment boldly, and enjoy the creative process.  Your unique artistic voice will emerge as you hone your skills and explore the boundless possibilities of the digital realm.",
    "keyTakeaways": [
      "Inspiration can come from anywhere; actively seek it out and document your ideas.",
      "Develop a strong concept before starting; plan your composition, colors, and style.",
      "Choose the right software and learn its tools for efficient workflow.",
      "Layer management is crucial for easy adjustments and experimentation.",
      "Seek feedback for improvement and embrace the iterative nature of the creative process.",
      "Protect your digital art through copyright and proper online presentation."
    ],
    "conclusion": "Creating digital art is a rewarding journey of exploration, experimentation, and self-expression. By understanding the phases involved – from inspiration to presentation – and embracing the iterative nature of the process, artists can unlock their creative potential and produce stunning digital masterpieces. Remember to protect your work and share your art with the world, inspiring others and growing your artistic community."
  },
  {
    "image": "https://image.pollinations.ai/prompt/A%20stylized%20illustration%20of%20an%20AI%20interface%20overlaid%20on%20an%20archaeological%20dig%20site%2C%20Featured%2C%20high%20detail%2C%20vibrant%2C%20professional%20photo?width=600&height=400&seed=286819623&nologo=true",
    "dataAiHint": "A stylized",
    "category": "Featured",
    "title": "Unearthing the Past: AI's Role in Ancient Civilization Studies",
    "articleContent": "Exploring Ancient Civilizations with Modern AI Technology\n\nThe study of ancient civilizations has always been a captivating pursuit, filled with mysteries waiting to be unraveled.  For centuries, historians and archaeologists painstakingly pieced together fragments of the past, relying on physical artifacts, deciphered texts, and limited historical accounts.  However, the advent of artificial intelligence (AI) is revolutionizing this field, offering unprecedented tools and capabilities to delve deeper into the lives, cultures, and legacies of ancient societies.  This exploration delves into how AI is transforming our understanding of the ancient world.\n\nAI-Powered Image Analysis and Artifact Recognition\n\nOne of the most significant contributions of AI lies in its ability to analyze vast quantities of visual data.  Archaeological digs often yield a plethora of artifacts, inscriptions, and imagery—too much for human researchers to analyze comprehensively.  AI algorithms, particularly those based on deep learning, can efficiently process images, identify patterns, and even recognize subtle details that might escape human observation.  This is particularly useful in deciphering faded inscriptions, identifying similar patterns across different artifacts, and even reconstructing damaged artifacts virtually using advanced image restoration techniques.\n\nDeciphering Ancient Languages and Scripts\n\nFor centuries, many ancient languages have remained undeciphered, leaving crucial historical information inaccessible.  AI is emerging as a powerful tool to crack these linguistic codes.  Machine learning models can be trained on known scripts, learning the statistical relationships between symbols and their meanings.  These trained models can then attempt to decipher unknown inscriptions, suggesting potential translations and helping researchers to understand the context of the text.  While AI cannot replace the expertise of linguists, it significantly accelerates the process, enabling them to focus on the most challenging aspects of deciphering.\n\nPredictive Modeling and Simulation of Ancient Societies\n\nBeyond analyzing static data, AI can be used to create dynamic models of ancient societies.  By integrating various data points, such as environmental records, archaeological findings, and historical narratives, AI algorithms can simulate past events, predict population dynamics, and model the impact of climate change or other factors on ancient civilizations.  Such simulations provide researchers with a better understanding of the complexities of ancient societies and can offer new hypotheses for testing.\n\nVirtual and Augmented Reality Applications\n\nAI is also playing a vital role in creating immersive experiences for both researchers and the public.  Virtual and augmented reality (VR/AR) technologies, powered by AI, can reconstruct ancient cities, buildings, and landscapes, allowing users to explore these environments in an engaging and interactive way.  This creates opportunities for educational programs, museum exhibits, and even virtual tourism, bringing the ancient world to life for a wider audience.\n\nEthical Considerations in AI-Driven Archaeology\n\nDespite its enormous potential, the use of AI in archaeology requires careful consideration of ethical implications.  One major concern is the potential for bias in algorithms.  If the training data reflects existing biases, the AI model may perpetuate or even amplify these biases, leading to skewed interpretations of the past.  Additionally, there are questions surrounding data ownership and access, particularly when dealing with sensitive cultural heritage.  Transparency and collaboration are crucial to ensure ethical and responsible use of AI in archaeology.\n\nThe Future of AI in Ancient Civilization Studies\n\nThe integration of AI into the study of ancient civilizations is still in its relatively early stages, but the potential benefits are immense.  As AI technologies continue to advance, we can expect even more sophisticated applications, ranging from automated artifact cataloging to advanced linguistic analysis and predictive modeling.  The collaboration between human experts and AI systems promises a deeper and more nuanced understanding of the past, enabling researchers to uncover new insights and shed light on the complexities of ancient societies.  This collaborative approach, where human expertise guides and interprets AI-generated results, will be critical for avoiding the pitfalls of relying solely on algorithmic analysis.\n\nAI's role is not to replace human researchers, but to augment their abilities, empowering them to tackle complex research questions with greater efficiency and accuracy.  By combining the strengths of human ingenuity with the analytical prowess of AI, we can unlock a treasure trove of information about the ancient world, enriching our understanding of human history and culture.\n\nAI is not just a tool, it's a collaborator, a partner in this ongoing quest to understand our shared past.  The possibilities are endless, and the discoveries that lie ahead are sure to be both fascinating and transformative.",
    "keyTakeaways": [
      "AI accelerates analysis of vast visual data from archaeological digs.",
      "AI aids in deciphering ancient languages and scripts previously unreadable.",
      "AI enables the creation of dynamic models simulating ancient societies and events.",
      "AI powers VR/AR experiences, bringing ancient civilizations to life.",
      "Ethical considerations, including bias and data ownership, must be addressed.",
      "The future holds more sophisticated AI applications for archaeology and history."
    ],
    "conclusion": "In conclusion, the application of artificial intelligence in the study of ancient civilizations marks a paradigm shift.  AI's ability to process vast amounts of data, decipher complex languages, and create dynamic simulations offers unprecedented opportunities for researchers to delve deeper into the past than ever before.  While ethical considerations must guide its development and application, the collaboration between human expertise and AI promises a more comprehensive and nuanced understanding of ancient societies, leaving a rich legacy for future generations."
  }
]